sorteia/__init__.py
sorteia/examples.py
sorteia/exceptions.py
sorteia/models.py
sorteia/operations.py
sorteia/schemas.py
sorteia/dependencies/__init__.py
sorteia/dependencies/sorting_resources.py
sorteia/dependencies/utils.py
tests/__init__.py
tests/conftest.py
tests/test_operations.py
sorteia-1.0.5.dist-info/METADATA
sorteia-1.0.5.dist-info/WHEEL
sorteia-1.0.5.dist-info/top_level.txt
sorteia-1.0.5.dist-info/zip-safe
sorteia-1.0.5.dist-info/RECORD
