Metadata-Version: 2.1
Name: sorteia
Version: 1.0.5
Summary: Package for custom sorting resources on a mongoDB collection.
Home-page: https://github.com/TeiaLabs/sorteia
Author: TeiaLabs
Author-email: contato@teialabs.com
Requires-Python: >=3.12
Requires-Dist: pymongo ==4.8.0
Requires-Dist: python-dotenv ==1.0.1
Requires-Dist: fastapi >=0.100.0
Requires-Dist: loguru ~=0.7
Requires-Dist: pydantic <3,>=2
Requires-Dist: redbaby ==1.0.3
Requires-Dist: tauth[first_party] ==2.0.2
Requires-Dist: melting-schemas ==3.0.1
Provides-Extra: test
Requires-Dist: pytest ; extra == 'test'
Requires-Dist: pytest-cov ; extra == 'test'
